server.py
mcp_add_1-0.1.7.dist-info/METADATA
mcp_add_1-0.1.7.dist-info/WHEEL
mcp_add_1-0.1.7.dist-info/entry_points.txt
mcp_add_1-0.1.7.dist-info/top_level.txt
mcp_add_1-0.1.7.dist-info/RECORD
