Metadata-Version: 2.4
Name: mcp-add-1
Version: 0.1.7
Summary: Add your description here
Requires-Python: >=3.13
Requires-Dist: mcp[cli]>=1.6.0
